odoo/addons/account_asset_operating_unit/README.rst
odoo/addons/account_asset_operating_unit/__init__.py
odoo/addons/account_asset_operating_unit/__manifest__.py
odoo/addons/account_asset_operating_unit/i18n/account_asset_operating_unit.pot
odoo/addons/account_asset_operating_unit/models/__init__.py
odoo/addons/account_asset_operating_unit/models/account_asset.py
odoo/addons/account_asset_operating_unit/models/account_asset_line.py
odoo/addons/account_asset_operating_unit/models/account_move.py
odoo/addons/account_asset_operating_unit/readme/CONTRIBUTORS.rst
odoo/addons/account_asset_operating_unit/readme/DESCRIPTION.rst
odoo/addons/account_asset_operating_unit/readme/USAGE.rst
odoo/addons/account_asset_operating_unit/report/__init__.py
odoo/addons/account_asset_operating_unit/report/account_asset_report_xls.py
odoo/addons/account_asset_operating_unit/security/account_asset_security.xml
odoo/addons/account_asset_operating_unit/static/description/icon.png
odoo/addons/account_asset_operating_unit/static/description/index.html
odoo/addons/account_asset_operating_unit/tests/__init__.py
odoo/addons/account_asset_operating_unit/tests/test_account_asset_operating_unit.py
odoo/addons/account_asset_operating_unit/views/account_asset_views.xml
odoo/addons/account_asset_operating_unit/wizard/__init__.py
odoo/addons/account_asset_operating_unit/wizard/account_asset_remove.py
odoo/addons/account_asset_operating_unit/wizard/wiz_account_asset_report.py
odoo/addons/account_asset_operating_unit/wizard/wiz_account_asset_report.xml
odoo14_addon_account_asset_operating_unit-14.0.1.0.2.dist-info/METADATA
odoo14_addon_account_asset_operating_unit-14.0.1.0.2.dist-info/WHEEL
odoo14_addon_account_asset_operating_unit-14.0.1.0.2.dist-info/top_level.txt
odoo14_addon_account_asset_operating_unit-14.0.1.0.2.dist-info/RECORD
